random_generator/__init__.py
random_generator/date.py
random_generator/financial.py
random_generator/germany.py
random_generator/network.py
random_generator/poland.py
tests/__init__.py
random_generator-1.0.2.dist-info/LICENSE
random_generator-1.0.2.dist-info/METADATA
random_generator-1.0.2.dist-info/WHEEL
random_generator-1.0.2.dist-info/top_level.txt
random_generator-1.0.2.dist-info/RECORD
