Metadata-Version: 2.1
Name: random_generator
Version: 1.0.2
Summary: Random generator
Author: Krzysztof Żyłka
Author-email: krzysztofzylka@yahoo.com
Classifier: Programming Language :: Python :: 3
Classifier: License :: OSI Approved :: MIT License
Classifier: Operating System :: OS Independent
License-File: LICENSE
